{
  "raceId": "202506040205",
  "raceName": "2歳新馬",
  "date": "2025-09-07",
  "predictions": [
    {
      "horseId": 1,
      "horseName": "ホールオブミラーズ",
      "score": 66.83434343434342,
      "ev": 1.008710932434185,
      "odds": 10.8,
      "waku": 1,
      "components": {
        "lastThreeF": 90.9090909090909,
        "training": 90.9090909090909,
        "courseRecord": 50,
        "prevClass": 50,
        "breeding": 50,
        "weightChange": 100,
        "jockey": 18.773946360153264
      }
    },
    {
      "horseId": 2,
      "horseName": "マイネルゼーロス",
      "score": 64.14646464646465,
      "ev": 1.017655297626767,
      "odds": 6.3,
      "waku": 2,
      "components": {
        "lastThreeF": 81.81818181818183,
        "training": 81.81818181818183,
        "courseRecord": 50,
        "prevClass": 50,
        "breeding": 50,
        "weightChange": 100,
        "jockey": 30.268199233716476
      }
    },
    {
      "horseId": 3,
      "horseName": "フォルテアンジェロ",
      "score": 61.858585858585855,
      "ev": 1.0182570354039684,
      "odds": 1.8,
      "waku": 3,
      "components": {
        "lastThreeF": 72.72727272727273,
        "training": 72.72727272727273,
        "courseRecord": 50,
        "prevClass": 50,
        "breeding": 50,
        "weightChange": 100,
        "jockey": 48.659003831417635
      }
    },
    {
      "horseId": 4,
      "horseName": "フロムドーン",
      "score": 55.68181818181818,
      "ev": 0.9807233173388665,
      "odds": 112,
      "waku": 4,
      "components": {
        "lastThreeF": 63.63636363636363,
        "training": 63.63636363636363,
        "courseRecord": 50,
        "prevClass": 50,
        "breeding": 50,
        "weightChange": 100,
        "jockey": 0
      }
    },
    {
      "horseId": 5,
      "horseName": "ダイシンレスター",
      "score": 52.682828282828275,
      "ev": 0.9801457657891324,
      "odds": 67,
      "waku": 5,
      "components": {
        "lastThreeF": 54.54545454545454,
        "training": 54.54545454545454,
        "courseRecord": 50,
        "prevClass": 50,
        "breeding": 50,
        "weightChange": 100,
        "jockey": 6.130268199233718
      }
    },
    {
      "horseId": 6,
      "horseName": "ソラネルマン",
      "score": 54.772727272727266,
      "ev": 0.9909648554013747,
      "odds": 3.5,
      "waku": 5,
      "components": {
        "lastThreeF": 45.45454545454545,
        "training": 45.45454545454545,
        "courseRecord": 50,
        "prevClass": 50,
        "breeding": 50,
        "weightChange": 100,
        "jockey": 100
      }
    },
    {
      "horseId": 7,
      "horseName": "ビリージェイ",
      "score": 46.70707070707071,
      "ev": 0.975979769160939,
      "odds": 35,
      "waku": 6,
      "components": {
        "lastThreeF": 36.36363636363637,
        "training": 36.36363636363637,
        "courseRecord": 50,
        "prevClass": 50,
        "breeding": 50,
        "weightChange": 100,
        "jockey": 18.773946360153264
      }
    },
    {
      "horseId": 8,
      "horseName": "ホワイトナイル",
      "score": 42.55252525252526,
      "ev": 0.9619485151082869,
      "odds": 16.9,
      "waku": 6,
      "components": {
        "lastThreeF": 27.27272727272727,
        "training": 27.27272727272727,
        "courseRecord": 50,
        "prevClass": 50,
        "breeding": 50,
        "weightChange": 100,
        "jockey": 4.980842911877397
      }
    },
    {
      "horseId": 9,
      "horseName": "サムシングニュー",
      "score": 39.37575757575758,
      "ev": 0.9775830631565297,
      "odds": 72.7,
      "waku": 7,
      "components": {
        "lastThreeF": 18.181818181818183,
        "training": 18.181818181818183,
        "courseRecord": 50,
        "prevClass": 50,
        "breeding": 50,
        "weightChange": 100,
        "jockey": 8.045977011494255
      }
    },
    {
      "horseId": 10,
      "horseName": "コッツォリーノ",
      "score": 70.5,
      "ev": 1.0157703281027104,
      "odds": 19.1,
      "waku": 7,
      "components": {
        "lastThreeF": 100,
        "training": 100,
        "courseRecord": 50,
        "prevClass": 50,
        "breeding": 50,
        "weightChange": 100,
        "jockey": 24.13793103448276
      }
    },
    {
      "horseId": 11,
      "horseName": "ハーディジェナー",
      "score": 35.73232323232323,
      "ev": 0.9768814031902477,
      "odds": 115.2,
      "waku": 8,
      "components": {
        "lastThreeF": 9.090909090909092,
        "training": 9.090909090909092,
        "courseRecord": 50,
        "prevClass": 50,
        "breeding": 50,
        "weightChange": 100,
        "jockey": 3.065134099616859
      }
    },
    {
      "horseId": 12,
      "horseName": "ダブルデライト",
      "score": 32.26666666666667,
      "ev": 0.9762139800285307,
      "odds": 315.1,
      "waku": 8,
      "components": {
        "lastThreeF": 0,
        "training": 0,
        "courseRecord": 50,
        "prevClass": 50,
        "breeding": 50,
        "weightChange": 100,
        "jockey": 1.149425287356323
      }
    }
  ],
  "results": {
    "raceId": "202506040205",
    "results": [
      {
        "rank": 1,
        "horseId": 3,
        "horseName": "フォルテアンジェロ",
        "time": "1:48.9",
        "lastThreeF": 33.9
      },
      {
        "rank": 2,
        "horseId": 6,
        "horseName": "ソラネルマン",
        "time": "1:48.9",
        "lastThreeF": 34.1
      },
      {
        "rank": 3,
        "horseId": 10,
        "horseName": "コッツォリーノ",
        "time": "1:49.0",
        "lastThreeF": 33.7
      },
      {
        "rank": 4,
        "horseId": 11,
        "horseName": "ハーディジェナー",
        "time": "1:49.4",
        "lastThreeF": 34.1
      },
      {
        "rank": 5,
        "horseId": 1,
        "horseName": "ホールオブミラーズ",
        "time": "1:49.4",
        "lastThreeF": 34.6
      },
      {
        "rank": 6,
        "horseId": 2,
        "horseName": "マイネルゼーロス",
        "time": "1:49.5",
        "lastThreeF": 34.9
      },
      {
        "rank": 7,
        "horseId": 5,
        "horseName": "ダイシンレスター",
        "time": "1:50.2",
        "lastThreeF": 35.8
      },
      {
        "rank": 8,
        "horseId": 9,
        "horseName": "サムシングニュー",
        "time": "1:50.9",
        "lastThreeF": 35.5
      },
      {
        "rank": 9,
        "horseId": 8,
        "horseName": "ホワイトナイル",
        "time": "1:51.0",
        "lastThreeF": 36
      },
      {
        "rank": 10,
        "horseId": 7,
        "horseName": "ビリージェイ",
        "time": "1:51.1",
        "lastThreeF": 35.6
      },
      {
        "rank": 11,
        "horseId": 4,
        "horseName": "フロムドーン",
        "time": "1:51.2",
        "lastThreeF": 35.4
      },
      {
        "rank": 12,
        "horseId": 12,
        "horseName": "ダブルデライト",
        "time": "1:51.7",
        "lastThreeF": 35.5
      }
    ],
    "payouts": {
      "tan": [
        {
          "horseId": 3,
          "payout": 180
        }
      ],
      "fuku": [
        {
          "horseId": 3,
          "payout": 110
        },
        {
          "horseId": 6,
          "payout": 130
        },
        {
          "horseId": 10,
          "payout": 270
        }
      ],
      "waku": [
        {
          "combination": "3-5",
          "payout": 340
        }
      ],
      "umaren": [
        {
          "combination": "3-6",
          "payout": 310
        }
      ],
      "umatan": [
        {
          "combination": "3-6",
          "payout": 480
        }
      ],
      "wide": [
        {
          "combination": "3-6",
          "payout": 180
        },
        {
          "combination": "3-10",
          "payout": 580
        },
        {
          "combination": "6-10",
          "payout": 740
        }
      ],
      "sanfuku": [
        {
          "combination": "3-6-10",
          "payout": 1360
        }
      ],
      "santan": [
        {
          "combination": "3-6-10",
          "payout": 3820
        }
      ]
    }
  },
  "accuracy": {
    "top1ScoreRank": 4,
    "top3EVCount": 2,
    "recommendedHits": [
      {
        "type": "単勝",
        "hit": false,
        "payout": 0
      },
      {
        "type": "馬連",
        "hit": false,
        "payout": 0
      },
      {
        "type": "三連複",
        "hit": false,
        "payout": 0
      },
      {
        "type": "三連単",
        "hit": false,
        "payout": 0
      }
    ]
  },
  "meta": {
    "raceClass": "新馬",
    "raceCondition": "サラ系2歳",
    "raceGrade": "OP",
    "weather": "晴",
    "trackCondition": "良",
    "handicap": "馬齢",
    "prize": 750,
    "ageLimit": "2歳",
    "distance": 1800,
    "surface": "turf",
    "startTime": "12:35",
    "raceDate": "20250907",
    "headCount": 12
  }
}