{
  "raceId": "202508040208",
  "raceName": "3歳以上2勝クラス",
  "date": "2025-11-09",
  "predictions": [
    {
      "horseId": 1,
      "horseName": "メイショウリリー",
      "score": 67.37499999999999,
      "ev": 0.99248515334745,
      "odds": 28.2,
      "waku": 1,
      "components": {
        "lastThreeF": 93.33333333333333,
        "training": 93.33333333333333,
        "courseRecord": 50,
        "prevClass": 50,
        "breeding": 50,
        "weightChange": 85,
        "jockey": 31.03448275862069
      }
    },
    {
      "horseId": 2,
      "horseName": "サツキノジョウ",
      "score": 66.69999999999999,
      "ev": 0.9919593280634496,
      "odds": 42.7,
      "waku": 1,
      "components": {
        "lastThreeF": 86.66666666666667,
        "training": 86.66666666666667,
        "courseRecord": 50,
        "prevClass": 50,
        "breeding": 50,
        "weightChange": 100,
        "jockey": 43.44827586206896
      }
    },
    {
      "horseId": 3,
      "horseName": "シンコーナホチャン",
      "score": 62.47,
      "ev": 1.0146566251348543,
      "odds": 5.5,
      "waku": 2,
      "components": {
        "lastThreeF": 80,
        "training": 80,
        "courseRecord": 50,
        "prevClass": 50,
        "breeding": 50,
        "weightChange": 70,
        "jockey": 49.65517241379309
      }
    },
    {
      "horseId": 4,
      "horseName": "ウィンターダフネ",
      "score": 65.21,
      "ev": 0.990798617436545,
      "odds": 24.9,
      "waku": 2,
      "components": {
        "lastThreeF": 100,
        "training": 100,
        "courseRecord": 50,
        "prevClass": 50,
        "breeding": 50,
        "weightChange": 30,
        "jockey": 18.62068965517241
      }
    },
    {
      "horseId": 5,
      "horseName": "フローラルセント",
      "score": 62.92999999999999,
      "ev": 0.9822556241193137,
      "odds": 77,
      "waku": 3,
      "components": {
        "lastThreeF": 73.33333333333333,
        "training": 73.33333333333333,
        "courseRecord": 50,
        "prevClass": 50,
        "breeding": 50,
        "weightChange": 70,
        "jockey": 100
      }
    },
    {
      "horseId": 6,
      "horseName": "リアルクィーン",
      "score": 58.8,
      "ev": 0.9814513061848982,
      "odds": 106,
      "waku": 3,
      "components": {
        "lastThreeF": 66.66666666666666,
        "training": 66.66666666666666,
        "courseRecord": 50,
        "prevClass": 50,
        "breeding": 50,
        "weightChange": 100,
        "jockey": 34.48275862068965
      }
    },
    {
      "horseId": 7,
      "horseName": "ルナビス",
      "score": 53.73,
      "ev": 0.9846392315160849,
      "odds": 15.7,
      "waku": 4,
      "components": {
        "lastThreeF": 60,
        "training": 60,
        "courseRecord": 50,
        "prevClass": 50,
        "breeding": 50,
        "weightChange": 70,
        "jockey": 26.20689655172414
      }
    },
    {
      "horseId": 8,
      "horseName": "メイショウタムシバ",
      "score": 53.86999999999999,
      "ev": 0.9849118816633444,
      "odds": 10.4,
      "waku": 4,
      "components": {
        "lastThreeF": 53.333333333333336,
        "training": 53.333333333333336,
        "courseRecord": 50,
        "prevClass": 50,
        "breeding": 50,
        "weightChange": 70,
        "jockey": 71.03448275862067
      }
    },
    {
      "horseId": 9,
      "horseName": "ブルーペクトライト",
      "score": 49.60999999999999,
      "ev": 0.9786462108729795,
      "odds": 32.8,
      "waku": 5,
      "components": {
        "lastThreeF": 46.666666666666664,
        "training": 46.666666666666664,
        "courseRecord": 50,
        "prevClass": 50,
        "breeding": 50,
        "weightChange": 70,
        "jockey": 40
      }
    },
    {
      "horseId": 10,
      "horseName": "タマモナポリ",
      "score": 47.605,
      "ev": 0.9792710787573483,
      "odds": 53.4,
      "waku": 5,
      "components": {
        "lastThreeF": 40,
        "training": 40,
        "courseRecord": 50,
        "prevClass": 50,
        "breeding": 50,
        "weightChange": 95,
        "jockey": 17.241379310344826
      }
    },
    {
      "horseId": 11,
      "horseName": "サイモンコーラル",
      "score": 39.53,
      "ev": 0.9776984716579766,
      "odds": 306.1,
      "waku": 6,
      "components": {
        "lastThreeF": 33.33333333333333,
        "training": 33.33333333333333,
        "courseRecord": 50,
        "prevClass": 50,
        "breeding": 50,
        "weightChange": 30,
        "jockey": 0
      }
    },
    {
      "horseId": 12,
      "horseName": "ツキノアカリ",
      "score": 42.895,
      "ev": 0.9734152230477012,
      "odds": 21.8,
      "waku": 6,
      "components": {
        "lastThreeF": 26.666666666666668,
        "training": 26.666666666666668,
        "courseRecord": 50,
        "prevClass": 50,
        "breeding": 50,
        "weightChange": 85,
        "jockey": 33.103448275862064
      }
    },
    {
      "horseId": 13,
      "horseName": "モズカトレア",
      "score": 40.835,
      "ev": 0.9390524109048699,
      "odds": 3.3,
      "waku": 7,
      "components": {
        "lastThreeF": 20,
        "training": 20,
        "courseRecord": 50,
        "prevClass": 50,
        "breeding": 50,
        "weightChange": 85,
        "jockey": 40
      }
    },
    {
      "horseId": 14,
      "horseName": "オーケーカルメン",
      "score": 38.565,
      "ev": 0.9775105378064728,
      "odds": 68.2,
      "waku": 7,
      "components": {
        "lastThreeF": 13.333333333333334,
        "training": 13.333333333333334,
        "courseRecord": 50,
        "prevClass": 50,
        "breeding": 50,
        "weightChange": 95,
        "jockey": 31.03448275862069
      }
    },
    {
      "horseId": 15,
      "horseName": "エルフストラック",
      "score": 33.56066666666667,
      "ev": 0.9107188672684715,
      "odds": 3.7,
      "waku": 8,
      "components": {
        "lastThreeF": 6.666666666666667,
        "training": 6.666666666666667,
        "courseRecord": 50,
        "prevClass": 50,
        "breeding": 50,
        "weightChange": 50,
        "jockey": 42.252873563218394
      }
    },
    {
      "horseId": 16,
      "horseName": "ノボリクレバー",
      "score": 37.88,
      "ev": 0.9380341437507329,
      "odds": 9.2,
      "waku": 8,
      "components": {
        "lastThreeF": 0,
        "training": 0,
        "courseRecord": 50,
        "prevClass": 50,
        "breeding": 50,
        "weightChange": 100,
        "jockey": 97.93103448275862
      }
    }
  ],
  "results": {
    "raceId": "202508040208",
    "results": [
      {
        "rank": 1,
        "horseId": 12,
        "horseName": "ツキノアカリ",
        "time": "1:49.7",
        "lastThreeF": 36.4
      },
      {
        "rank": 2,
        "horseId": 13,
        "horseName": "モズカトレア",
        "time": "1:49.8",
        "lastThreeF": 36.9
      },
      {
        "rank": 3,
        "horseId": 15,
        "horseName": "エルフストラック",
        "time": "1:50.1",
        "lastThreeF": 37.4
      },
      {
        "rank": 4,
        "horseId": 10,
        "horseName": "タマモナポリ",
        "time": "1:50.3",
        "lastThreeF": 37.1
      },
      {
        "rank": 5,
        "horseId": 8,
        "horseName": "メイショウタムシバ",
        "time": "1:50.4",
        "lastThreeF": 37.3
      },
      {
        "rank": 6,
        "horseId": 6,
        "horseName": "リアルクィーン",
        "time": "1:50.4",
        "lastThreeF": 36.4
      },
      {
        "rank": 7,
        "horseId": 2,
        "horseName": "サツキノジョウ",
        "time": "1:50.5",
        "lastThreeF": 36.8
      },
      {
        "rank": 8,
        "horseId": 5,
        "horseName": "フローラルセント",
        "time": "1:50.7",
        "lastThreeF": 37.8
      },
      {
        "rank": 9,
        "horseId": 3,
        "horseName": "シンコーナホチャン",
        "time": "1:50.7",
        "lastThreeF": 36.3
      },
      {
        "rank": 10,
        "horseId": 4,
        "horseName": "ウィンターダフネ",
        "time": "1:50.8",
        "lastThreeF": 36.9
      },
      {
        "rank": 11,
        "horseId": 7,
        "horseName": "ルナビス",
        "time": "1:50.9",
        "lastThreeF": 36.7
      },
      {
        "rank": 12,
        "horseId": 16,
        "horseName": "ノボリクレバー",
        "time": "1:51.1",
        "lastThreeF": 37.5
      },
      {
        "rank": 13,
        "horseId": 11,
        "horseName": "サイモンコーラル",
        "time": "1:51.8",
        "lastThreeF": 38.2
      },
      {
        "rank": 14,
        "horseId": 9,
        "horseName": "ブルーペクトライト",
        "time": "1:51.9",
        "lastThreeF": 37.6
      },
      {
        "rank": 15,
        "horseId": 14,
        "horseName": "オーケーカルメン",
        "time": "1:51.9",
        "lastThreeF": 39.3
      },
      {
        "rank": 16,
        "horseId": 1,
        "horseName": "メイショウリリー",
        "time": "1:53.5",
        "lastThreeF": 39.8
      }
    ],
    "payouts": {
      "tan": [
        {
          "horseId": 12,
          "payout": 2180
        }
      ],
      "fuku": [
        {
          "horseId": 12,
          "payout": 380
        },
        {
          "horseId": 13,
          "payout": 150
        },
        {
          "horseId": 15,
          "payout": 180
        }
      ],
      "waku": [
        {
          "combination": "6-7",
          "payout": 3470
        }
      ],
      "umaren": [
        {
          "combination": "12-13",
          "payout": 4190
        }
      ],
      "umatan": [
        {
          "combination": "12-13",
          "payout": 10030
        }
      ],
      "wide": [
        {
          "combination": "12-13",
          "payout": 1280
        },
        {
          "combination": "12-15",
          "payout": 1720
        },
        {
          "combination": "13-15",
          "payout": 300
        }
      ],
      "sanfuku": [
        {
          "combination": "12-13-15",
          "payout": 4200
        }
      ],
      "santan": [
        {
          "combination": "12-13-15",
          "payout": 43170
        }
      ]
    }
  },
  "accuracy": {
    "top1ScoreRank": 11,
    "top3EVCount": 0,
    "recommendedHits": [
      {
        "type": "単勝",
        "hit": false,
        "payout": 0
      },
      {
        "type": "馬連",
        "hit": false,
        "payout": 0
      },
      {
        "type": "三連複",
        "hit": false,
        "payout": 0
      },
      {
        "type": "三連単",
        "hit": false,
        "payout": 0
      }
    ]
  },
  "meta": {
    "raceClass": "2勝クラス",
    "raceCondition": "サラ系3歳以上",
    "raceGrade": "OP",
    "weather": "雨",
    "trackCondition": "重",
    "handicap": "定量",
    "prize": 1140,
    "ageLimit": "3歳以上",
    "sexLimit": "牝",
    "courseTurn": "右",
    "distance": 1800,
    "surface": "dirt",
    "startTime": "14:01",
    "raceDate": "20251109",
    "headCount": 16
  }
}