{
  "raceId": "202503020403",
  "raceName": "3歳未勝利",
  "date": "2025-07-06",
  "predictions": [
    {
      "horseId": 1,
      "horseName": "フェスティヴイリス",
      "score": 66.4915770609319,
      "ev": 0.9829381460049444,
      "odds": 224,
      "waku": 1,
      "components": {
        "lastThreeF": 100,
        "training": 100,
        "courseRecord": 50,
        "prevClass": 50,
        "breeding": 50,
        "weightChange": 30,
        "jockey": 40.71684587813621
      }
    },
    {
      "horseId": 2,
      "horseName": "ワンダーカフェ",
      "score": 70.56903225806451,
      "ev": 0.9949262016718771,
      "odds": 28,
      "waku": 1,
      "components": {
        "lastThreeF": 93.33333333333333,
        "training": 93.33333333333333,
        "courseRecord": 50,
        "prevClass": 50,
        "breeding": 50,
        "weightChange": 100,
        "jockey": 67.74193548387098
      }
    },
    {
      "horseId": 3,
      "horseName": "フライエフェクト",
      "score": 64.63575268817203,
      "ev": 1.005770336993618,
      "odds": 16.1,
      "waku": 2,
      "components": {
        "lastThreeF": 86.66666666666667,
        "training": 86.66666666666667,
        "courseRecord": 50,
        "prevClass": 50,
        "breeding": 50,
        "weightChange": 95,
        "jockey": 13.978494623655916
      }
    },
    {
      "horseId": 4,
      "horseName": "テンペストヒロイン",
      "score": 61.02919354838709,
      "ev": 1.0175051552678518,
      "odds": 1.8,
      "waku": 2,
      "components": {
        "lastThreeF": 80,
        "training": 80,
        "courseRecord": 50,
        "prevClass": 50,
        "breeding": 50,
        "weightChange": 85,
        "jockey": 6.451612903225805
      }
    },
    {
      "horseId": 5,
      "horseName": "キャナルクルーズ",
      "score": 59.56704301075268,
      "ev": 1.0054519645637954,
      "odds": 5.5,
      "waku": 3,
      "components": {
        "lastThreeF": 73.33333333333333,
        "training": 73.33333333333333,
        "courseRecord": 50,
        "prevClass": 50,
        "breeding": 50,
        "weightChange": 85,
        "jockey": 23.65591397849462
      }
    },
    {
      "horseId": 6,
      "horseName": "ニシノヒミチュ",
      "score": 59.438548387096766,
      "ev": 0.9956574488599499,
      "odds": 16.6,
      "waku": 3,
      "components": {
        "lastThreeF": 66.66666666666666,
        "training": 66.66666666666666,
        "courseRecord": 50,
        "prevClass": 50,
        "breeding": 50,
        "weightChange": 95,
        "jockey": 51.61290322580645
      }
    },
    {
      "horseId": 7,
      "horseName": "ライラックダンサー",
      "score": 53.67322580645161,
      "ev": 0.9804439097812924,
      "odds": 107.2,
      "waku": 4,
      "components": {
        "lastThreeF": 60,
        "training": 60,
        "courseRecord": 50,
        "prevClass": 50,
        "breeding": 50,
        "weightChange": 30,
        "jockey": 74.19354838709678
      }
    },
    {
      "horseId": 8,
      "horseName": "アユツリー",
      "score": 52.07193548387096,
      "ev": 0.9821172085439911,
      "odds": 6.6,
      "waku": 4,
      "components": {
        "lastThreeF": 53.333333333333336,
        "training": 53.333333333333336,
        "courseRecord": 50,
        "prevClass": 50,
        "breeding": 50,
        "weightChange": 50,
        "jockey": 64.51612903225808
      }
    },
    {
      "horseId": 9,
      "horseName": "バレドラパン",
      "score": 48.03838709677419,
      "ev": 0.9793474646500044,
      "odds": 77.2,
      "waku": 5,
      "components": {
        "lastThreeF": 46.666666666666664,
        "training": 46.666666666666664,
        "courseRecord": 50,
        "prevClass": 50,
        "breeding": 50,
        "weightChange": 70,
        "jockey": 12.903225806451612
      }
    },
    {
      "horseId": 10,
      "horseName": "ヴィクトリアランド",
      "score": 47.578870967741935,
      "ev": 0.9792580505161872,
      "odds": 236.6,
      "waku": 5,
      "components": {
        "lastThreeF": 40,
        "training": 40,
        "courseRecord": 50,
        "prevClass": 50,
        "breeding": 50,
        "weightChange": 85,
        "jockey": 29.03225806451613
      }
    },
    {
      "horseId": 11,
      "horseName": "ジェンダアネモス",
      "score": 45.99198924731182,
      "ev": 0.9631883190604454,
      "odds": 6.6,
      "waku": 6,
      "components": {
        "lastThreeF": 33.33333333333333,
        "training": 33.33333333333333,
        "courseRecord": 50,
        "prevClass": 50,
        "breeding": 50,
        "weightChange": 85,
        "jockey": 44.086021505376344
      }
    },
    {
      "horseId": 12,
      "horseName": "イオリ",
      "score": 42.9131182795699,
      "ev": 0.9783501732756276,
      "odds": 62.5,
      "waku": 6,
      "components": {
        "lastThreeF": 26.666666666666668,
        "training": 26.666666666666668,
        "courseRecord": 50,
        "prevClass": 50,
        "breeding": 50,
        "weightChange": 100,
        "jockey": 15.053763440860212
      }
    },
    {
      "horseId": 13,
      "horseName": "カフェアリス",
      "score": 37.45,
      "ev": 0.9772871420607327,
      "odds": 247.9,
      "waku": 7,
      "components": {
        "lastThreeF": 20,
        "training": 20,
        "courseRecord": 50,
        "prevClass": 50,
        "breeding": 50,
        "weightChange": 70,
        "jockey": 0
      }
    },
    {
      "horseId": 14,
      "horseName": "オーセンティアン",
      "score": 40.35344086021506,
      "ev": 0.9778521029689657,
      "odds": 62.4,
      "waku": 7,
      "components": {
        "lastThreeF": 13.333333333333334,
        "training": 13.333333333333334,
        "courseRecord": 50,
        "prevClass": 50,
        "breeding": 50,
        "weightChange": 70,
        "jockey": 92.47311827956989
      }
    },
    {
      "horseId": 15,
      "horseName": "ロンドンキッド",
      "score": 34.46811827956989,
      "ev": 0.9767069178763516,
      "odds": 75.9,
      "waku": 8,
      "components": {
        "lastThreeF": 6.666666666666667,
        "training": 6.666666666666667,
        "courseRecord": 50,
        "prevClass": 50,
        "breeding": 50,
        "weightChange": 85,
        "jockey": 15.053763440860212
      }
    },
    {
      "horseId": 16,
      "horseName": "ミスベレザ",
      "score": 38,
      "ev": 0.9773941628386608,
      "odds": 214.8,
      "waku": 8,
      "components": {
        "lastThreeF": 0,
        "training": 0,
        "courseRecord": 50,
        "prevClass": 50,
        "breeding": 50,
        "weightChange": 100,
        "jockey": 100
      }
    }
  ],
  "results": {
    "raceId": "202503020403",
    "results": [
      {
        "rank": 1,
        "horseId": 6,
        "horseName": "ニシノヒミチュ",
        "time": "1:09.8",
        "lastThreeF": 35.9
      },
      {
        "rank": 2,
        "horseId": 5,
        "horseName": "キャナルクルーズ",
        "time": "1:09.9",
        "lastThreeF": 35.6
      },
      {
        "rank": 3,
        "horseId": 7,
        "horseName": "ライラックダンサー",
        "time": "1:10.0",
        "lastThreeF": 35.4
      },
      {
        "rank": 4,
        "horseId": 8,
        "horseName": "アユツリー",
        "time": "1:10.3",
        "lastThreeF": 35.9
      },
      {
        "rank": 5,
        "horseId": 12,
        "horseName": "イオリ",
        "time": "1:10.4",
        "lastThreeF": 36.1
      },
      {
        "rank": 6,
        "horseId": 3,
        "horseName": "フライエフェクト",
        "time": "1:10.4",
        "lastThreeF": 35.5
      },
      {
        "rank": 7,
        "horseId": 9,
        "horseName": "バレドラパン",
        "time": "1:10.6",
        "lastThreeF": 35.2
      },
      {
        "rank": 8,
        "horseId": 15,
        "horseName": "ロンドンキッド",
        "time": "1:10.6",
        "lastThreeF": 36.1
      },
      {
        "rank": 9,
        "horseId": 1,
        "horseName": "フェスティヴイリス",
        "time": "1:10.9",
        "lastThreeF": 35.5
      },
      {
        "rank": 10,
        "horseId": 2,
        "horseName": "ワンダーカフェ",
        "time": "1:11.1",
        "lastThreeF": 35.2
      },
      {
        "rank": 11,
        "horseId": 16,
        "horseName": "ミスベレザ",
        "time": "1:11.1",
        "lastThreeF": 35.5
      },
      {
        "rank": 12,
        "horseId": 4,
        "horseName": "テンペストヒロイン",
        "time": "1:11.2",
        "lastThreeF": 37.3
      },
      {
        "rank": 13,
        "horseId": 10,
        "horseName": "ヴィクトリアランド",
        "time": "1:11.3",
        "lastThreeF": 35.2
      },
      {
        "rank": 14,
        "horseId": 13,
        "horseName": "カフェアリス",
        "time": "1:11.3",
        "lastThreeF": 36.2
      },
      {
        "rank": 15,
        "horseId": 14,
        "horseName": "オーセンティアン",
        "time": "1:11.8",
        "lastThreeF": 37.2
      },
      {
        "rank": 16,
        "horseId": 11,
        "horseName": "ジェンダアネモス",
        "time": "1:11.8",
        "lastThreeF": 37.7
      }
    ],
    "payouts": {
      "tan": [
        {
          "horseId": 6,
          "payout": 1660
        }
      ],
      "fuku": [
        {
          "horseId": 6,
          "payout": 420
        },
        {
          "horseId": 5,
          "payout": 220
        },
        {
          "horseId": 7,
          "payout": 2180
        }
      ],
      "waku": [
        {
          "combination": "3-3",
          "payout": 3880
        }
      ],
      "umaren": [
        {
          "combination": "5-6",
          "payout": 2890
        }
      ],
      "umatan": [
        {
          "combination": "6-5",
          "payout": 6440
        }
      ],
      "wide": [
        {
          "combination": "5-6",
          "payout": 850
        },
        {
          "combination": "6-7",
          "payout": 11320
        },
        {
          "combination": "5-7",
          "payout": 6560
        }
      ],
      "sanfuku": [
        {
          "combination": "5-6-7",
          "payout": 81320
        }
      ],
      "santan": [
        {
          "combination": "6-5-7",
          "payout": 547660
        }
      ]
    }
  },
  "accuracy": {
    "top1ScoreRank": 6,
    "top3EVCount": 1,
    "recommendedHits": [
      {
        "type": "単勝",
        "hit": false,
        "payout": 0
      },
      {
        "type": "馬連",
        "hit": false,
        "payout": 0
      },
      {
        "type": "三連複",
        "hit": false,
        "payout": 0
      },
      {
        "type": "三連単",
        "hit": false,
        "payout": 0
      }
    ]
  },
  "meta": {
    "raceClass": "未勝利",
    "raceCondition": "サラ系3歳",
    "raceGrade": "OP",
    "weather": "曇",
    "trackCondition": "良",
    "handicap": "馬齢",
    "prize": 560,
    "ageLimit": "3歳",
    "sexLimit": "牝",
    "distance": 1200,
    "surface": "turf",
    "startTime": "11:15",
    "raceDate": "20250706",
    "headCount": 16
  }
}