{
  "raceId": "202605010306",
  "raceName": "3歳未勝利",
  "date": "2026-02-07",
  "predictions": [
    {
      "horseId": 1,
      "horseName": "クレアノア",
      "score": 67.1242238267148,
      "ev": 0.9944750162707031,
      "odds": 29,
      "waku": 1,
      "components": {
        "lastThreeF": 100,
        "training": 100,
        "courseRecord": 50,
        "prevClass": 50,
        "breeding": 50,
        "weightChange": 30,
        "jockey": 51.624548736462096
      }
    },
    {
      "horseId": 2,
      "horseName": "ターンザテーブルス",
      "score": 67.56416967509024,
      "ev": 1.0170801415845296,
      "odds": 10.4,
      "waku": 1,
      "components": {
        "lastThreeF": 93.33333333333333,
        "training": 93.33333333333333,
        "courseRecord": 50,
        "prevClass": 50,
        "breeding": 50,
        "weightChange": 85,
        "jockey": 34.29602888086643
      }
    },
    {
      "horseId": 3,
      "horseName": "サザンテイオー",
      "score": 59.545018050541515,
      "ev": 1.00081018007435,
      "odds": 15.1,
      "waku": 2,
      "components": {
        "lastThreeF": 86.66666666666667,
        "training": 86.66666666666667,
        "courseRecord": 50,
        "prevClass": 50,
        "breeding": 50,
        "weightChange": 30,
        "jockey": 5.776173285198557
      }
    },
    {
      "horseId": 4,
      "horseName": "レヴェランジェ",
      "score": 64.67330324909747,
      "ev": 1.029943835231212,
      "odds": 6.8,
      "waku": 2,
      "components": {
        "lastThreeF": 80,
        "training": 80,
        "courseRecord": 50,
        "prevClass": 50,
        "breeding": 50,
        "weightChange": 95,
        "jockey": 57.039711191335755
      }
    },
    {
      "horseId": 5,
      "horseName": "ハクシンスマイル",
      "score": 54.68783393501804,
      "ev": 0.9810955496897453,
      "odds": 339.2,
      "waku": 3,
      "components": {
        "lastThreeF": 73.33333333333333,
        "training": 73.33333333333333,
        "courseRecord": 50,
        "prevClass": 50,
        "breeding": 50,
        "weightChange": 30,
        "jockey": 6.859205776173287
      }
    },
    {
      "horseId": 6,
      "horseName": "レッドアヴィオン",
      "score": 57.47003610108303,
      "ev": 1.0132005476716153,
      "odds": 4.6,
      "waku": 3,
      "components": {
        "lastThreeF": 66.66666666666666,
        "training": 66.66666666666666,
        "courseRecord": 50,
        "prevClass": 50,
        "breeding": 50,
        "weightChange": 100,
        "jockey": 11.552346570397114
      }
    },
    {
      "horseId": 7,
      "horseName": "テンユウ",
      "score": 51.861696750902524,
      "ev": 0.9883545291562714,
      "odds": 6.7,
      "waku": 4,
      "components": {
        "lastThreeF": 60,
        "training": 60,
        "courseRecord": 50,
        "prevClass": 50,
        "breeding": 50,
        "weightChange": 30,
        "jockey": 42.96028880866427
      }
    },
    {
      "horseId": 8,
      "horseName": "レアリゼソンレーヴ",
      "score": 47.956931407942236,
      "ev": 0.9789196994736931,
      "odds": 22.5,
      "waku": 4,
      "components": {
        "lastThreeF": 53.333333333333336,
        "training": 53.333333333333336,
        "courseRecord": 50,
        "prevClass": 50,
        "breeding": 50,
        "weightChange": 30,
        "jockey": 18.05054151624549
      }
    },
    {
      "horseId": 9,
      "horseName": "パンジー",
      "score": 44.449999999999996,
      "ev": 0.9790184077192601,
      "odds": 254.8,
      "waku": 5,
      "components": {
        "lastThreeF": 46.666666666666664,
        "training": 46.666666666666664,
        "courseRecord": 50,
        "prevClass": 50,
        "breeding": 50,
        "weightChange": 30,
        "jockey": 0
      }
    },
    {
      "horseId": 10,
      "horseName": "コスモペンタス",
      "score": 46.502220216606496,
      "ev": 0.9794347802421637,
      "odds": 148,
      "waku": 5,
      "components": {
        "lastThreeF": 40,
        "training": 40,
        "courseRecord": 50,
        "prevClass": 50,
        "breeding": 50,
        "weightChange": 85,
        "jockey": 10.469314079422386
      }
    },
    {
      "horseId": 11,
      "horseName": "ケイツースクード",
      "score": 44.64752707581227,
      "ev": 0.9790584837531244,
      "odds": 381.3,
      "waku": 6,
      "components": {
        "lastThreeF": 33.33333333333333,
        "training": 33.33333333333333,
        "courseRecord": 50,
        "prevClass": 50,
        "breeding": 50,
        "weightChange": 95,
        "jockey": 8.664259927797834
      }
    },
    {
      "horseId": 12,
      "horseName": "アイアンパイク",
      "score": 40.14415162454874,
      "ev": 0.950316788083322,
      "odds": 7.3,
      "waku": 6,
      "components": {
        "lastThreeF": 26.666666666666668,
        "training": 26.666666666666668,
        "courseRecord": 50,
        "prevClass": 50,
        "breeding": 50,
        "weightChange": 50,
        "jockey": 28.51985559566787
      }
    },
    {
      "horseId": 13,
      "horseName": "ジュラトリー",
      "score": 40.30148014440434,
      "ev": 0.950827511228582,
      "odds": 6.9,
      "waku": 7,
      "components": {
        "lastThreeF": 20,
        "training": 20,
        "courseRecord": 50,
        "prevClass": 50,
        "breeding": 50,
        "weightChange": 50,
        "jockey": 73.6462093862816
      }
    },
    {
      "horseId": 14,
      "horseName": "ジュナベーラ",
      "score": 40.790000000000006,
      "ev": 0.9524133546433728,
      "odds": 5.1,
      "waku": 7,
      "components": {
        "lastThreeF": 13.333333333333334,
        "training": 13.333333333333334,
        "courseRecord": 50,
        "prevClass": 50,
        "breeding": 50,
        "weightChange": 70,
        "jockey": 100
      }
    },
    {
      "horseId": 15,
      "horseName": "トーケンジンロック",
      "score": 33.241913357400726,
      "ev": 0.9767444123290294,
      "odds": 178.2,
      "waku": 8,
      "components": {
        "lastThreeF": 6.666666666666667,
        "training": 6.666666666666667,
        "courseRecord": 50,
        "prevClass": 50,
        "breeding": 50,
        "weightChange": 70,
        "jockey": 12.274368231046932
      }
    },
    {
      "horseId": 16,
      "horseName": "トゥントゥントゥン",
      "score": 27.648772563176895,
      "ev": 0.9756096266346866,
      "odds": 172,
      "waku": 8,
      "components": {
        "lastThreeF": 0,
        "training": 0,
        "courseRecord": 50,
        "prevClass": 50,
        "breeding": 50,
        "weightChange": 30,
        "jockey": 7.220216606498198
      }
    }
  ],
  "results": {
    "raceId": "202605010306",
    "results": [
      {
        "rank": 1,
        "horseId": 2,
        "horseName": "ターンザテーブルス",
        "time": "1:34.9",
        "lastThreeF": 33.6
      },
      {
        "rank": 2,
        "horseId": 3,
        "horseName": "サザンテイオー",
        "time": "1:34.9",
        "lastThreeF": 34.1
      },
      {
        "rank": 3,
        "horseId": 12,
        "horseName": "アイアンパイク",
        "time": "1:35.0",
        "lastThreeF": 34.5
      },
      {
        "rank": 4,
        "horseId": 1,
        "horseName": "クレアノア",
        "time": "1:35.1",
        "lastThreeF": 33.5
      },
      {
        "rank": 5,
        "horseId": 13,
        "horseName": "ジュラトリー",
        "time": "1:35.1",
        "lastThreeF": 34.6
      },
      {
        "rank": 6,
        "horseId": 9,
        "horseName": "パンジー",
        "time": "1:35.1",
        "lastThreeF": 35
      },
      {
        "rank": 7,
        "horseId": 7,
        "horseName": "テンユウ",
        "time": "1:35.2",
        "lastThreeF": 34.5
      },
      {
        "rank": 8,
        "horseId": 4,
        "horseName": "レヴェランジェ",
        "time": "1:35.3",
        "lastThreeF": 34.2
      },
      {
        "rank": 9,
        "horseId": 8,
        "horseName": "レアリゼソンレーヴ",
        "time": "1:35.4",
        "lastThreeF": 34.1
      },
      {
        "rank": 10,
        "horseId": 6,
        "horseName": "レッドアヴィオン",
        "time": "1:35.5",
        "lastThreeF": 35.3
      },
      {
        "rank": 11,
        "horseId": 14,
        "horseName": "ジュナベーラ",
        "time": "1:35.7",
        "lastThreeF": 34.7
      },
      {
        "rank": 12,
        "horseId": 16,
        "horseName": "トゥントゥントゥン",
        "time": "1:35.8",
        "lastThreeF": 34.6
      },
      {
        "rank": 13,
        "horseId": 10,
        "horseName": "コスモペンタス",
        "time": "1:36.1",
        "lastThreeF": 34.6
      },
      {
        "rank": 14,
        "horseId": 11,
        "horseName": "ケイツースクード",
        "time": "1:36.1",
        "lastThreeF": 35.4
      },
      {
        "rank": 15,
        "horseId": 5,
        "horseName": "ハクシンスマイル",
        "time": "1:36.9",
        "lastThreeF": 35.8
      },
      {
        "rank": 16,
        "horseId": 15,
        "horseName": "トーケンジンロック",
        "time": "1:38.2",
        "lastThreeF": 36.3
      }
    ],
    "payouts": {
      "tan": [
        {
          "horseId": 2,
          "payout": 1040
        }
      ],
      "fuku": [
        {
          "horseId": 2,
          "payout": 350
        },
        {
          "horseId": 3,
          "payout": 390
        },
        {
          "horseId": 12,
          "payout": 290
        }
      ],
      "waku": [
        {
          "combination": "1-2",
          "payout": 1670
        }
      ],
      "umaren": [
        {
          "combination": "2-3",
          "payout": 7330
        }
      ],
      "umatan": [
        {
          "combination": "2-3",
          "payout": 15060
        }
      ],
      "wide": [
        {
          "combination": "2-3",
          "payout": 2160
        },
        {
          "combination": "2-12",
          "payout": 1590
        },
        {
          "combination": "3-12",
          "payout": 1600
        }
      ],
      "sanfuku": [
        {
          "combination": "2-3-12",
          "payout": 18900
        }
      ],
      "santan": [
        {
          "combination": "2-3-12",
          "payout": 128170
        }
      ]
    }
  },
  "accuracy": {
    "top1ScoreRank": 1,
    "top3EVCount": 2,
    "recommendedHits": [
      {
        "type": "単勝",
        "hit": true,
        "payout": 1040
      },
      {
        "type": "馬連",
        "hit": false,
        "payout": 0
      },
      {
        "type": "三連複",
        "hit": false,
        "payout": 0
      },
      {
        "type": "三連単",
        "hit": false,
        "payout": 0
      }
    ]
  },
  "meta": {
    "raceClass": "未勝利",
    "raceCondition": "サラ系3歳",
    "raceGrade": "OP",
    "weather": "雪",
    "trackCondition": "良",
    "handicap": "馬齢",
    "prize": 590,
    "ageLimit": "3歳",
    "distance": 1600,
    "surface": "turf",
    "startTime": "13:00",
    "raceDate": "20260207",
    "headCount": 16
  }
}