{
  "raceId": "202606010604",
  "raceName": "4歳以上障害未勝利",
  "date": "2026-01-17",
  "predictions": [
    {
      "horseId": 1,
      "horseName": "ゴーツウキリシマ",
      "score": 67.73,
      "ev": 1.0339327676347592,
      "odds": 7.7,
      "waku": 1,
      "components": {
        "lastThreeF": 100,
        "training": 100,
        "courseRecord": 50,
        "prevClass": 50,
        "breeding": 50,
        "weightChange": 70,
        "jockey": 13.103448275862068
      }
    },
    {
      "horseId": 2,
      "horseName": "ワキノノーブル",
      "score": 64.95545454545454,
      "ev": 0.9828230660009254,
      "odds": 264.9,
      "waku": 2,
      "components": {
        "lastThreeF": 90.9090909090909,
        "training": 90.9090909090909,
        "courseRecord": 50,
        "prevClass": 50,
        "breeding": 50,
        "weightChange": 50,
        "jockey": 47.58620689655173
      }
    },
    {
      "horseId": 3,
      "horseName": "スティルシャイニン",
      "score": 63.401909090909086,
      "ev": 0.9825163755768729,
      "odds": 167.9,
      "waku": 3,
      "components": {
        "lastThreeF": 81.81818181818183,
        "training": 81.81818181818183,
        "courseRecord": 50,
        "prevClass": 50,
        "breeding": 50,
        "weightChange": 85,
        "jockey": 35.793103448275865
      }
    },
    {
      "horseId": 4,
      "horseName": "ローガンパス",
      "score": 57.14636363636363,
      "ev": 0.9851257926066352,
      "odds": 25.5,
      "waku": 4,
      "components": {
        "lastThreeF": 72.72727272727273,
        "training": 72.72727272727273,
        "courseRecord": 50,
        "prevClass": 50,
        "breeding": 50,
        "weightChange": 30,
        "jockey": 53.10344827586208
      }
    },
    {
      "horseId": 5,
      "horseName": "ロイヤルダンス",
      "score": 56.511818181818185,
      "ev": 0.9811561804847452,
      "odds": 112,
      "waku": 5,
      "components": {
        "lastThreeF": 63.63636363636363,
        "training": 63.63636363636363,
        "courseRecord": 50,
        "prevClass": 50,
        "breeding": 50,
        "weightChange": 30,
        "jockey": 100
      }
    },
    {
      "horseId": 6,
      "horseName": "サラフィエル",
      "score": 55.052272727272715,
      "ev": 0.993888750466987,
      "odds": 7.2,
      "waku": 5,
      "components": {
        "lastThreeF": 54.54545454545454,
        "training": 54.54545454545454,
        "courseRecord": 50,
        "prevClass": 50,
        "breeding": 50,
        "weightChange": 95,
        "jockey": 53.10344827586208
      }
    },
    {
      "horseId": 7,
      "horseName": "インヴァリアンス",
      "score": 49.983727272727265,
      "ev": 0.9798674489813926,
      "odds": 125.8,
      "waku": 6,
      "components": {
        "lastThreeF": 45.45454545454545,
        "training": 45.45454545454545,
        "courseRecord": 50,
        "prevClass": 50,
        "breeding": 50,
        "weightChange": 85,
        "jockey": 35.793103448275865
      }
    },
    {
      "horseId": 8,
      "horseName": "コレクテイニア",
      "score": 45.79318181818182,
      "ev": 0.9608035974672481,
      "odds": 1.6,
      "waku": 6,
      "components": {
        "lastThreeF": 36.36363636363637,
        "training": 36.36363636363637,
        "courseRecord": 50,
        "prevClass": 50,
        "breeding": 50,
        "weightChange": 85,
        "jockey": 21.379310344827587
      }
    },
    {
      "horseId": 9,
      "horseName": "アルカンサス",
      "score": 42.51863636363636,
      "ev": 0.9735749651311407,
      "odds": 36.3,
      "waku": 7,
      "components": {
        "lastThreeF": 27.27272727272727,
        "training": 27.27272727272727,
        "courseRecord": 50,
        "prevClass": 50,
        "breeding": 50,
        "weightChange": 85,
        "jockey": 22.758620689655178
      }
    },
    {
      "horseId": 10,
      "horseName": "ホウオウユニコーン",
      "score": 37.84409090909091,
      "ev": 0.9774709241720834,
      "odds": 53.9,
      "waku": 7,
      "components": {
        "lastThreeF": 18.181818181818183,
        "training": 18.181818181818183,
        "courseRecord": 50,
        "prevClass": 50,
        "breeding": 50,
        "weightChange": 85,
        "jockey": 0
      }
    },
    {
      "horseId": 11,
      "horseName": "フォーディアライフ",
      "score": 37.63454545454545,
      "ev": 0.9285911425470075,
      "odds": 4.5,
      "waku": 8,
      "components": {
        "lastThreeF": 9.090909090909092,
        "training": 9.090909090909092,
        "courseRecord": 50,
        "prevClass": 50,
        "breeding": 50,
        "weightChange": 100,
        "jockey": 35.86206896551724
      }
    },
    {
      "horseId": 12,
      "horseName": "キュピドン",
      "score": 29.290000000000003,
      "ev": 0.9631289338698586,
      "odds": 25.8,
      "waku": 8,
      "components": {
        "lastThreeF": 0,
        "training": 0,
        "courseRecord": 50,
        "prevClass": 50,
        "breeding": 50,
        "weightChange": 50,
        "jockey": 11.03448275862069
      }
    }
  ],
  "results": {
    "raceId": "202606010604",
    "results": [
      {
        "rank": 1,
        "horseId": 8,
        "horseName": "コレクテイニア",
        "time": "3:14.9",
        "lastThreeF": 13.5
      },
      {
        "rank": 2,
        "horseId": 9,
        "horseName": "アルカンサス",
        "time": "3:16.1",
        "lastThreeF": 13.6
      },
      {
        "rank": 3,
        "horseId": 1,
        "horseName": "ゴーツウキリシマ",
        "time": "3:16.5",
        "lastThreeF": 13.6
      },
      {
        "rank": 4,
        "horseId": 6,
        "horseName": "サラフィエル",
        "time": "3:17.0",
        "lastThreeF": 13.7
      },
      {
        "rank": 5,
        "horseId": 10,
        "horseName": "ホウオウユニコーン",
        "time": "3:17.2",
        "lastThreeF": 13.7
      },
      {
        "rank": 6,
        "horseId": 12,
        "horseName": "キュピドン",
        "time": "3:17.5",
        "lastThreeF": 13.7
      },
      {
        "rank": 7,
        "horseId": 3,
        "horseName": "スティルシャイニン",
        "time": "3:17.8",
        "lastThreeF": 13.7
      },
      {
        "rank": 8,
        "horseId": 11,
        "horseName": "フォーディアライフ",
        "time": "3:17.9",
        "lastThreeF": 13.7
      },
      {
        "rank": 9,
        "horseId": 7,
        "horseName": "インヴァリアンス",
        "time": "3:20.5",
        "lastThreeF": 13.9
      },
      {
        "rank": 10,
        "horseId": 2,
        "horseName": "ワキノノーブル",
        "time": "3:21.2",
        "lastThreeF": 14
      },
      {
        "rank": 11,
        "horseId": 4,
        "horseName": "ローガンパス",
        "time": "3:22.1",
        "lastThreeF": 14
      },
      {
        "rank": 12,
        "horseId": 5,
        "horseName": "ロイヤルダンス",
        "time": "3:25.1",
        "lastThreeF": 14.2
      }
    ],
    "payouts": {
      "tan": [
        {
          "horseId": 8,
          "payout": 160
        }
      ],
      "fuku": [
        {
          "horseId": 8,
          "payout": 110
        },
        {
          "horseId": 9,
          "payout": 350
        },
        {
          "horseId": 1,
          "payout": 160
        }
      ],
      "waku": [
        {
          "combination": "6-7",
          "payout": 1410
        }
      ],
      "umaren": [
        {
          "combination": "8-9",
          "payout": 2530
        }
      ],
      "umatan": [
        {
          "combination": "8-9",
          "payout": 2760
        }
      ],
      "wide": [
        {
          "combination": "8-9",
          "payout": 680
        },
        {
          "combination": "1-8",
          "payout": 260
        },
        {
          "combination": "1-9",
          "payout": 1560
        }
      ],
      "sanfuku": [
        {
          "combination": "1-8-9",
          "payout": 3280
        }
      ],
      "santan": [
        {
          "combination": "8-9-1",
          "payout": 15910
        }
      ]
    }
  },
  "accuracy": {
    "top1ScoreRank": 8,
    "top3EVCount": 1,
    "recommendedHits": [
      {
        "type": "単勝",
        "hit": false,
        "payout": 0
      },
      {
        "type": "馬連",
        "hit": false,
        "payout": 0
      },
      {
        "type": "三連複",
        "hit": false,
        "payout": 0
      },
      {
        "type": "三連単",
        "hit": false,
        "payout": 0
      }
    ]
  },
  "meta": {
    "raceClass": "未勝利",
    "raceCondition": "障害4歳以上",
    "weather": "晴",
    "trackCondition": "良",
    "handicap": "定量",
    "prize": 840,
    "ageLimit": "4歳以上",
    "distance": 2880,
    "surface": "turf",
    "startTime": "11:35",
    "raceDate": "20260117",
    "headCount": 12
  }
}